{"nodes": [{"id": "c_users_boris_onedrive_documents_github_spann_mesh_daemon_src_ble_gatt_server_cpp", "label": "gatt_server.cpp", "file_type": "code", "source_file": "C:\\Users\\boris\\OneDrive\\Documents\\GitHub\\spann\\mesh-daemon\\src\\ble\\gatt_server.cpp", "source_location": "L1"}, {"id": "gatt_server_start", "label": "Start()", "file_type": "code", "source_file": "C:\\Users\\boris\\OneDrive\\Documents\\GitHub\\spann\\mesh-daemon\\src\\ble\\gatt_server.cpp", "source_location": "L7"}, {"id": "gatt_server_stop", "label": "Stop()", "file_type": "code", "source_file": "C:\\Users\\boris\\OneDrive\\Documents\\GitHub\\spann\\mesh-daemon\\src\\ble\\gatt_server.cpp", "source_location": "L14"}, {"id": "gatt_server_isrunning", "label": "IsRunning()", "file_type": "code", "source_file": "C:\\Users\\boris\\OneDrive\\Documents\\GitHub\\spann\\mesh-daemon\\src\\ble\\gatt_server.cpp", "source_location": "L21"}], "edges": [{"source": "c_users_boris_onedrive_documents_github_spann_mesh_daemon_src_ble_gatt_server_cpp", "target": "gatt_server", "relation": "imports", "confidence": "EXTRACTED", "source_file": "C:\\Users\\boris\\OneDrive\\Documents\\GitHub\\spann\\mesh-daemon\\src\\ble\\gatt_server.cpp", "source_location": "L1", "weight": 1.0}, {"source": "c_users_boris_onedrive_documents_github_spann_mesh_daemon_src_ble_gatt_server_cpp", "target": "logger", "relation": "imports", "confidence": "EXTRACTED", "source_file": "C:\\Users\\boris\\OneDrive\\Documents\\GitHub\\spann\\mesh-daemon\\src\\ble\\gatt_server.cpp", "source_location": "L3", "weight": 1.0}, {"source": "c_users_boris_onedrive_documents_github_spann_mesh_daemon_src_ble_gatt_server_cpp", "target": "gatt_server_start", "relation": "contains", "confidence": "EXTRACTED", "source_file": "C:\\Users\\boris\\OneDrive\\Documents\\GitHub\\spann\\mesh-daemon\\src\\ble\\gatt_server.cpp", "source_location": "L7", "weight": 1.0}, {"source": "c_users_boris_onedrive_documents_github_spann_mesh_daemon_src_ble_gatt_server_cpp", "target": "gatt_server_stop", "relation": "contains", "confidence": "EXTRACTED", "source_file": "C:\\Users\\boris\\OneDrive\\Documents\\GitHub\\spann\\mesh-daemon\\src\\ble\\gatt_server.cpp", "source_location": "L14", "weight": 1.0}, {"source": "c_users_boris_onedrive_documents_github_spann_mesh_daemon_src_ble_gatt_server_cpp", "target": "gatt_server_isrunning", "relation": "contains", "confidence": "EXTRACTED", "source_file": "C:\\Users\\boris\\OneDrive\\Documents\\GitHub\\spann\\mesh-daemon\\src\\ble\\gatt_server.cpp", "source_location": "L21", "weight": 1.0}], "raw_calls": [{"caller_nid": "gatt_server_start", "callee": "exchange", "source_file": "C:\\Users\\boris\\OneDrive\\Documents\\GitHub\\spann\\mesh-daemon\\src\\ble\\gatt_server.cpp", "source_location": "L8"}, {"caller_nid": "gatt_server_start", "callee": "Info", "source_file": "C:\\Users\\boris\\OneDrive\\Documents\\GitHub\\spann\\mesh-daemon\\src\\ble\\gatt_server.cpp", "source_location": "L11"}, {"caller_nid": "gatt_server_start", "callee": "Logger::Instance", "source_file": "C:\\Users\\boris\\OneDrive\\Documents\\GitHub\\spann\\mesh-daemon\\src\\ble\\gatt_server.cpp", "source_location": "L11"}, {"caller_nid": "gatt_server_stop", "callee": "exchange", "source_file": "C:\\Users\\boris\\OneDrive\\Documents\\GitHub\\spann\\mesh-daemon\\src\\ble\\gatt_server.cpp", "source_location": "L15"}, {"caller_nid": "gatt_server_stop", "callee": "Info", "source_file": "C:\\Users\\boris\\OneDrive\\Documents\\GitHub\\spann\\mesh-daemon\\src\\ble\\gatt_server.cpp", "source_location": "L18"}, {"caller_nid": "gatt_server_stop", "callee": "Logger::Instance", "source_file": "C:\\Users\\boris\\OneDrive\\Documents\\GitHub\\spann\\mesh-daemon\\src\\ble\\gatt_server.cpp", "source_location": "L18"}, {"caller_nid": "gatt_server_isrunning", "callee": "load", "source_file": "C:\\Users\\boris\\OneDrive\\Documents\\GitHub\\spann\\mesh-daemon\\src\\ble\\gatt_server.cpp", "source_location": "L21"}]}