{"nodes": [{"id": "c_users_boris_onedrive_documents_github_spann_src_views_supportview_jsx", "label": "SupportView.jsx", "file_type": "code", "source_file": "C:\\Users\\boris\\OneDrive\\Documents\\GitHub\\spann\\src\\views\\SupportView.jsx", "source_location": "L1"}, {"id": "supportview_statusdot", "label": "StatusDot()", "file_type": "code", "source_file": "C:\\Users\\boris\\OneDrive\\Documents\\GitHub\\spann\\src\\views\\SupportView.jsx", "source_location": "L258"}, {"id": "supportview_categorycard", "label": "CategoryCard()", "file_type": "code", "source_file": "C:\\Users\\boris\\OneDrive\\Documents\\GitHub\\spann\\src\\views\\SupportView.jsx", "source_location": "L267"}, {"id": "supportview_contactmodal", "label": "ContactModal()", "file_type": "code", "source_file": "C:\\Users\\boris\\OneDrive\\Documents\\GitHub\\spann\\src\\views\\SupportView.jsx", "source_location": "L295"}, {"id": "supportview_supportview", "label": "SupportView()", "file_type": "code", "source_file": "C:\\Users\\boris\\OneDrive\\Documents\\GitHub\\spann\\src\\views\\SupportView.jsx", "source_location": "L429"}], "edges": [{"source": "c_users_boris_onedrive_documents_github_spann_src_views_supportview_jsx", "target": "react", "relation": "imports_from", "confidence": "EXTRACTED", "source_file": "C:\\Users\\boris\\OneDrive\\Documents\\GitHub\\spann\\src\\views\\SupportView.jsx", "source_location": "L1", "weight": 1.0}, {"source": "c_users_boris_onedrive_documents_github_spann_src_views_supportview_jsx", "target": "supportview_statusdot", "relation": "contains", "confidence": "EXTRACTED", "source_file": "C:\\Users\\boris\\OneDrive\\Documents\\GitHub\\spann\\src\\views\\SupportView.jsx", "source_location": "L258", "weight": 1.0}, {"source": "c_users_boris_onedrive_documents_github_spann_src_views_supportview_jsx", "target": "supportview_categorycard", "relation": "contains", "confidence": "EXTRACTED", "source_file": "C:\\Users\\boris\\OneDrive\\Documents\\GitHub\\spann\\src\\views\\SupportView.jsx", "source_location": "L267", "weight": 1.0}, {"source": "c_users_boris_onedrive_documents_github_spann_src_views_supportview_jsx", "target": "supportview_contactmodal", "relation": "contains", "confidence": "EXTRACTED", "source_file": "C:\\Users\\boris\\OneDrive\\Documents\\GitHub\\spann\\src\\views\\SupportView.jsx", "source_location": "L295", "weight": 1.0}, {"source": "c_users_boris_onedrive_documents_github_spann_src_views_supportview_jsx", "target": "supportview_supportview", "relation": "contains", "confidence": "EXTRACTED", "source_file": "C:\\Users\\boris\\OneDrive\\Documents\\GitHub\\spann\\src\\views\\SupportView.jsx", "source_location": "L429", "weight": 1.0}], "raw_calls": [{"caller_nid": "supportview_categorycard", "callee": "join", "source_file": "C:\\Users\\boris\\OneDrive\\Documents\\GitHub\\spann\\src\\views\\SupportView.jsx", "source_location": "L272"}, {"caller_nid": "supportview_contactmodal", "callee": "useState", "source_file": "C:\\Users\\boris\\OneDrive\\Documents\\GitHub\\spann\\src\\views\\SupportView.jsx", "source_location": "L296"}, {"caller_nid": "supportview_contactmodal", "callee": "useState", "source_file": "C:\\Users\\boris\\OneDrive\\Documents\\GitHub\\spann\\src\\views\\SupportView.jsx", "source_location": "L297"}, {"caller_nid": "supportview_supportview", "callee": "useState", "source_file": "C:\\Users\\boris\\OneDrive\\Documents\\GitHub\\spann\\src\\views\\SupportView.jsx", "source_location": "L430"}, {"caller_nid": "supportview_supportview", "callee": "useState", "source_file": "C:\\Users\\boris\\OneDrive\\Documents\\GitHub\\spann\\src\\views\\SupportView.jsx", "source_location": "L431"}, {"caller_nid": "supportview_supportview", "callee": "useState", "source_file": "C:\\Users\\boris\\OneDrive\\Documents\\GitHub\\spann\\src\\views\\SupportView.jsx", "source_location": "L432"}, {"caller_nid": "supportview_supportview", "callee": "useState", "source_file": "C:\\Users\\boris\\OneDrive\\Documents\\GitHub\\spann\\src\\views\\SupportView.jsx", "source_location": "L433"}, {"caller_nid": "supportview_supportview", "callee": "reduce", "source_file": "C:\\Users\\boris\\OneDrive\\Documents\\GitHub\\spann\\src\\views\\SupportView.jsx", "source_location": "L435"}, {"caller_nid": "supportview_supportview", "callee": "trim", "source_file": "C:\\Users\\boris\\OneDrive\\Documents\\GitHub\\spann\\src\\views\\SupportView.jsx", "source_location": "L441"}, {"caller_nid": "supportview_supportview", "callee": "filter", "source_file": "C:\\Users\\boris\\OneDrive\\Documents\\GitHub\\spann\\src\\views\\SupportView.jsx", "source_location": "L442"}, {"caller_nid": "supportview_supportview", "callee": "trim", "source_file": "C:\\Users\\boris\\OneDrive\\Documents\\GitHub\\spann\\src\\views\\SupportView.jsx", "source_location": "L449"}, {"caller_nid": "supportview_supportview", "callee": "filter", "source_file": "C:\\Users\\boris\\OneDrive\\Documents\\GitHub\\spann\\src\\views\\SupportView.jsx", "source_location": "L450"}, {"caller_nid": "supportview_supportview", "callee": "filter", "source_file": "C:\\Users\\boris\\OneDrive\\Documents\\GitHub\\spann\\src\\views\\SupportView.jsx", "source_location": "L459"}, {"caller_nid": "supportview_supportview", "callee": "find", "source_file": "C:\\Users\\boris\\OneDrive\\Documents\\GitHub\\spann\\src\\views\\SupportView.jsx", "source_location": "L463"}, {"caller_nid": "supportview_supportview", "callee": "some", "source_file": "C:\\Users\\boris\\OneDrive\\Documents\\GitHub\\spann\\src\\views\\SupportView.jsx", "source_location": "L465"}, {"caller_nid": "supportview_supportview", "callee": "some", "source_file": "C:\\Users\\boris\\OneDrive\\Documents\\GitHub\\spann\\src\\views\\SupportView.jsx", "source_location": "L467"}, {"caller_nid": "supportview_supportview", "callee": "map", "source_file": "C:\\Users\\boris\\OneDrive\\Documents\\GitHub\\spann\\src\\views\\SupportView.jsx", "source_location": "L520"}, {"caller_nid": "supportview_supportview", "callee": "map", "source_file": "C:\\Users\\boris\\OneDrive\\Documents\\GitHub\\spann\\src\\views\\SupportView.jsx", "source_location": "L541"}, {"caller_nid": "supportview_supportview", "callee": "map", "source_file": "C:\\Users\\boris\\OneDrive\\Documents\\GitHub\\spann\\src\\views\\SupportView.jsx", "source_location": "L564"}, {"caller_nid": "supportview_supportview", "callee": "map", "source_file": "C:\\Users\\boris\\OneDrive\\Documents\\GitHub\\spann\\src\\views\\SupportView.jsx", "source_location": "L602"}]}