{"nodes": [{"id": "c_users_boris_onedrive_documents_github_spann_backend_app_schemas_user_py", "label": "user.py", "file_type": "code", "source_file": "C:\\Users\\boris\\OneDrive\\Documents\\GitHub\\spann\\backend\\app\\schemas\\user.py", "source_location": "L1"}, {"id": "user_loginrequest", "label": "LoginRequest", "file_type": "code", "source_file": "C:\\Users\\boris\\OneDrive\\Documents\\GitHub\\spann\\backend\\app\\schemas\\user.py", "source_location": "L10"}, {"id": "basemodel", "label": "BaseModel", "file_type": "code", "source_file": "", "source_location": ""}, {"id": "user_magiclinkrequest", "label": "MagicLinkRequest", "file_type": "code", "source_file": "C:\\Users\\boris\\OneDrive\\Documents\\GitHub\\spann\\backend\\app\\schemas\\user.py", "source_location": "L19"}, {"id": "user_userprofilepatchrequest", "label": "UserProfilePatchRequest", "file_type": "code", "source_file": "C:\\Users\\boris\\OneDrive\\Documents\\GitHub\\spann\\backend\\app\\schemas\\user.py", "source_location": "L27"}, {"id": "user_userpreferencespatchrequest", "label": "UserPreferencesPatchRequest", "file_type": "code", "source_file": "C:\\Users\\boris\\OneDrive\\Documents\\GitHub\\spann\\backend\\app\\schemas\\user.py", "source_location": "L40"}, {"id": "user_userpreferencesresponse", "label": "UserPreferencesResponse", "file_type": "code", "source_file": "C:\\Users\\boris\\OneDrive\\Documents\\GitHub\\spann\\backend\\app\\schemas\\user.py", "source_location": "L50"}, {"id": "user_rationale_1", "label": "User and authentication request/response schemas.", "file_type": "rationale", "source_file": "C:\\Users\\boris\\OneDrive\\Documents\\GitHub\\spann\\backend\\app\\schemas\\user.py", "source_location": "L1"}, {"id": "user_rationale_11", "label": "Credentials for email/password login.", "file_type": "rationale", "source_file": "C:\\Users\\boris\\OneDrive\\Documents\\GitHub\\spann\\backend\\app\\schemas\\user.py", "source_location": "L11"}, {"id": "user_rationale_20", "label": "Request payload for sending a magic link email.", "file_type": "rationale", "source_file": "C:\\Users\\boris\\OneDrive\\Documents\\GitHub\\spann\\backend\\app\\schemas\\user.py", "source_location": "L20"}, {"id": "user_rationale_28", "label": "Patch payload for mutable user profile fields.", "file_type": "rationale", "source_file": "C:\\Users\\boris\\OneDrive\\Documents\\GitHub\\spann\\backend\\app\\schemas\\user.py", "source_location": "L28"}, {"id": "user_rationale_41", "label": "Patch payload for user preferences and accessibility settings.", "file_type": "rationale", "source_file": "C:\\Users\\boris\\OneDrive\\Documents\\GitHub\\spann\\backend\\app\\schemas\\user.py", "source_location": "L41"}, {"id": "user_rationale_51", "label": "Response body for updated preferences.", "file_type": "rationale", "source_file": "C:\\Users\\boris\\OneDrive\\Documents\\GitHub\\spann\\backend\\app\\schemas\\user.py", "source_location": "L51"}], "edges": [{"source": "c_users_boris_onedrive_documents_github_spann_backend_app_schemas_user_py", "target": "typing", "relation": "imports_from", "confidence": "EXTRACTED", "source_file": "C:\\Users\\boris\\OneDrive\\Documents\\GitHub\\spann\\backend\\app\\schemas\\user.py", "source_location": "L5", "weight": 1.0}, {"source": "c_users_boris_onedrive_documents_github_spann_backend_app_schemas_user_py", "target": "pydantic", "relation": "imports_from", "confidence": "EXTRACTED", "source_file": "C:\\Users\\boris\\OneDrive\\Documents\\GitHub\\spann\\backend\\app\\schemas\\user.py", "source_location": "L7", "weight": 1.0}, {"source": "c_users_boris_onedrive_documents_github_spann_backend_app_schemas_user_py", "target": "user_loginrequest", "relation": "contains", "confidence": "EXTRACTED", "source_file": "C:\\Users\\boris\\OneDrive\\Documents\\GitHub\\spann\\backend\\app\\schemas\\user.py", "source_location": "L10", "weight": 1.0}, {"source": "user_loginrequest", "target": "basemodel", "relation": "inherits", "confidence": "EXTRACTED", "source_file": "C:\\Users\\boris\\OneDrive\\Documents\\GitHub\\spann\\backend\\app\\schemas\\user.py", "source_location": "L10", "weight": 1.0}, {"source": "c_users_boris_onedrive_documents_github_spann_backend_app_schemas_user_py", "target": "user_magiclinkrequest", "relation": "contains", "confidence": "EXTRACTED", "source_file": "C:\\Users\\boris\\OneDrive\\Documents\\GitHub\\spann\\backend\\app\\schemas\\user.py", "source_location": "L19", "weight": 1.0}, {"source": "user_magiclinkrequest", "target": "basemodel", "relation": "inherits", "confidence": "EXTRACTED", "source_file": "C:\\Users\\boris\\OneDrive\\Documents\\GitHub\\spann\\backend\\app\\schemas\\user.py", "source_location": "L19", "weight": 1.0}, {"source": "c_users_boris_onedrive_documents_github_spann_backend_app_schemas_user_py", "target": "user_userprofilepatchrequest", "relation": "contains", "confidence": "EXTRACTED", "source_file": "C:\\Users\\boris\\OneDrive\\Documents\\GitHub\\spann\\backend\\app\\schemas\\user.py", "source_location": "L27", "weight": 1.0}, {"source": "user_userprofilepatchrequest", "target": "basemodel", "relation": "inherits", "confidence": "EXTRACTED", "source_file": "C:\\Users\\boris\\OneDrive\\Documents\\GitHub\\spann\\backend\\app\\schemas\\user.py", "source_location": "L27", "weight": 1.0}, {"source": "c_users_boris_onedrive_documents_github_spann_backend_app_schemas_user_py", "target": "user_userpreferencespatchrequest", "relation": "contains", "confidence": "EXTRACTED", "source_file": "C:\\Users\\boris\\OneDrive\\Documents\\GitHub\\spann\\backend\\app\\schemas\\user.py", "source_location": "L40", "weight": 1.0}, {"source": "user_userpreferencespatchrequest", "target": "basemodel", "relation": "inherits", "confidence": "EXTRACTED", "source_file": "C:\\Users\\boris\\OneDrive\\Documents\\GitHub\\spann\\backend\\app\\schemas\\user.py", "source_location": "L40", "weight": 1.0}, {"source": "c_users_boris_onedrive_documents_github_spann_backend_app_schemas_user_py", "target": "user_userpreferencesresponse", "relation": "contains", "confidence": "EXTRACTED", "source_file": "C:\\Users\\boris\\OneDrive\\Documents\\GitHub\\spann\\backend\\app\\schemas\\user.py", "source_location": "L50", "weight": 1.0}, {"source": "user_userpreferencesresponse", "target": "basemodel", "relation": "inherits", "confidence": "EXTRACTED", "source_file": "C:\\Users\\boris\\OneDrive\\Documents\\GitHub\\spann\\backend\\app\\schemas\\user.py", "source_location": "L50", "weight": 1.0}, {"source": "user_rationale_1", "target": "c_users_boris_onedrive_documents_github_spann_backend_app_schemas_user_py", "relation": "rationale_for", "confidence": "EXTRACTED", "source_file": "C:\\Users\\boris\\OneDrive\\Documents\\GitHub\\spann\\backend\\app\\schemas\\user.py", "source_location": "L1", "weight": 1.0}, {"source": "user_rationale_11", "target": "user_loginrequest", "relation": "rationale_for", "confidence": "EXTRACTED", "source_file": "C:\\Users\\boris\\OneDrive\\Documents\\GitHub\\spann\\backend\\app\\schemas\\user.py", "source_location": "L11", "weight": 1.0}, {"source": "user_rationale_20", "target": "user_magiclinkrequest", "relation": "rationale_for", "confidence": "EXTRACTED", "source_file": "C:\\Users\\boris\\OneDrive\\Documents\\GitHub\\spann\\backend\\app\\schemas\\user.py", "source_location": "L20", "weight": 1.0}, {"source": "user_rationale_28", "target": "user_userprofilepatchrequest", "relation": "rationale_for", "confidence": "EXTRACTED", "source_file": "C:\\Users\\boris\\OneDrive\\Documents\\GitHub\\spann\\backend\\app\\schemas\\user.py", "source_location": "L28", "weight": 1.0}, {"source": "user_rationale_41", "target": "user_userpreferencespatchrequest", "relation": "rationale_for", "confidence": "EXTRACTED", "source_file": "C:\\Users\\boris\\OneDrive\\Documents\\GitHub\\spann\\backend\\app\\schemas\\user.py", "source_location": "L41", "weight": 1.0}, {"source": "user_rationale_51", "target": "user_userpreferencesresponse", "relation": "rationale_for", "confidence": "EXTRACTED", "source_file": "C:\\Users\\boris\\OneDrive\\Documents\\GitHub\\spann\\backend\\app\\schemas\\user.py", "source_location": "L51", "weight": 1.0}], "raw_calls": []}