{"nodes": [{"id": "c_users_boris_onedrive_documents_github_spann_mesh_daemon_src_routing_message_store_h", "label": "message_store.h", "file_type": "code", "source_file": "C:\\Users\\boris\\OneDrive\\Documents\\GitHub\\spann\\mesh-daemon\\src\\routing\\message_store.h", "source_location": "L1"}, {"id": "message_store_routing", "label": "routing()", "file_type": "code", "source_file": "C:\\Users\\boris\\OneDrive\\Documents\\GitHub\\spann\\mesh-daemon\\src\\routing\\message_store.h", "source_location": "L12"}], "edges": [{"source": "c_users_boris_onedrive_documents_github_spann_mesh_daemon_src_routing_message_store_h", "target": "memory", "relation": "imports", "confidence": "EXTRACTED", "source_file": "C:\\Users\\boris\\OneDrive\\Documents\\GitHub\\spann\\mesh-daemon\\src\\routing\\message_store.h", "source_location": "L3", "weight": 1.0}, {"source": "c_users_boris_onedrive_documents_github_spann_mesh_daemon_src_routing_message_store_h", "target": "mutex", "relation": "imports", "confidence": "EXTRACTED", "source_file": "C:\\Users\\boris\\OneDrive\\Documents\\GitHub\\spann\\mesh-daemon\\src\\routing\\message_store.h", "source_location": "L4", "weight": 1.0}, {"source": "c_users_boris_onedrive_documents_github_spann_mesh_daemon_src_routing_message_store_h", "target": "string", "relation": "imports", "confidence": "EXTRACTED", "source_file": "C:\\Users\\boris\\OneDrive\\Documents\\GitHub\\spann\\mesh-daemon\\src\\routing\\message_store.h", "source_location": "L5", "weight": 1.0}, {"source": "c_users_boris_onedrive_documents_github_spann_mesh_daemon_src_routing_message_store_h", "target": "vector", "relation": "imports", "confidence": "EXTRACTED", "source_file": "C:\\Users\\boris\\OneDrive\\Documents\\GitHub\\spann\\mesh-daemon\\src\\routing\\message_store.h", "source_location": "L6", "weight": 1.0}, {"source": "c_users_boris_onedrive_documents_github_spann_mesh_daemon_src_routing_message_store_h", "target": "db", "relation": "imports", "confidence": "EXTRACTED", "source_file": "C:\\Users\\boris\\OneDrive\\Documents\\GitHub\\spann\\mesh-daemon\\src\\routing\\message_store.h", "source_location": "L8", "weight": 1.0}, {"source": "c_users_boris_onedrive_documents_github_spann_mesh_daemon_src_routing_message_store_h", "target": "types", "relation": "imports", "confidence": "EXTRACTED", "source_file": "C:\\Users\\boris\\OneDrive\\Documents\\GitHub\\spann\\mesh-daemon\\src\\routing\\message_store.h", "source_location": "L10", "weight": 1.0}, {"source": "c_users_boris_onedrive_documents_github_spann_mesh_daemon_src_routing_message_store_h", "target": "message_store_routing", "relation": "contains", "confidence": "EXTRACTED", "source_file": "C:\\Users\\boris\\OneDrive\\Documents\\GitHub\\spann\\mesh-daemon\\src\\routing\\message_store.h", "source_location": "L12", "weight": 1.0}], "raw_calls": []}