{"nodes": [{"id": "c_users_boris_onedrive_documents_github_spann_mesh_daemon_src_main_cpp", "label": "main.cpp", "file_type": "code", "source_file": "C:\\Users\\boris\\OneDrive\\Documents\\GitHub\\spann\\mesh-daemon\\src\\main.cpp", "source_location": "L1"}, {"id": "main_handlesignal", "label": "HandleSignal()", "file_type": "code", "source_file": "C:\\Users\\boris\\OneDrive\\Documents\\GitHub\\spann\\mesh-daemon\\src\\main.cpp", "source_location": "L28"}, {"id": "main_getenvordefault", "label": "GetEnvOrDefault()", "file_type": "code", "source_file": "C:\\Users\\boris\\OneDrive\\Documents\\GitHub\\spann\\mesh-daemon\\src\\main.cpp", "source_location": "L30"}, {"id": "main_parseportordefault", "label": "ParsePortOrDefault()", "file_type": "code", "source_file": "C:\\Users\\boris\\OneDrive\\Documents\\GitHub\\spann\\mesh-daemon\\src\\main.cpp", "source_location": "L35"}, {"id": "main_main", "label": "main()", "file_type": "code", "source_file": "C:\\Users\\boris\\OneDrive\\Documents\\GitHub\\spann\\mesh-daemon\\src\\main.cpp", "source_location": "L49"}], "edges": [{"source": "c_users_boris_onedrive_documents_github_spann_mesh_daemon_src_main_cpp", "target": "atomic", "relation": "imports", "confidence": "EXTRACTED", "source_file": "C:\\Users\\boris\\OneDrive\\Documents\\GitHub\\spann\\mesh-daemon\\src\\main.cpp", "source_location": "L1", "weight": 1.0}, {"source": "c_users_boris_onedrive_documents_github_spann_mesh_daemon_src_main_cpp", "target": "chrono", "relation": "imports", "confidence": "EXTRACTED", "source_file": "C:\\Users\\boris\\OneDrive\\Documents\\GitHub\\spann\\mesh-daemon\\src\\main.cpp", "source_location": "L2", "weight": 1.0}, {"source": "c_users_boris_onedrive_documents_github_spann_mesh_daemon_src_main_cpp", "target": "csignal", "relation": "imports", "confidence": "EXTRACTED", "source_file": "C:\\Users\\boris\\OneDrive\\Documents\\GitHub\\spann\\mesh-daemon\\src\\main.cpp", "source_location": "L3", "weight": 1.0}, {"source": "c_users_boris_onedrive_documents_github_spann_mesh_daemon_src_main_cpp", "target": "cstdlib", "relation": "imports", "confidence": "EXTRACTED", "source_file": "C:\\Users\\boris\\OneDrive\\Documents\\GitHub\\spann\\mesh-daemon\\src\\main.cpp", "source_location": "L4", "weight": 1.0}, {"source": "c_users_boris_onedrive_documents_github_spann_mesh_daemon_src_main_cpp", "target": "exception", "relation": "imports", "confidence": "EXTRACTED", "source_file": "C:\\Users\\boris\\OneDrive\\Documents\\GitHub\\spann\\mesh-daemon\\src\\main.cpp", "source_location": "L5", "weight": 1.0}, {"source": "c_users_boris_onedrive_documents_github_spann_mesh_daemon_src_main_cpp", "target": "string", "relation": "imports", "confidence": "EXTRACTED", "source_file": "C:\\Users\\boris\\OneDrive\\Documents\\GitHub\\spann\\mesh-daemon\\src\\main.cpp", "source_location": "L6", "weight": 1.0}, {"source": "c_users_boris_onedrive_documents_github_spann_mesh_daemon_src_main_cpp", "target": "thread", "relation": "imports", "confidence": "EXTRACTED", "source_file": "C:\\Users\\boris\\OneDrive\\Documents\\GitHub\\spann\\mesh-daemon\\src\\main.cpp", "source_location": "L7", "weight": 1.0}, {"source": "c_users_boris_onedrive_documents_github_spann_mesh_daemon_src_main_cpp", "target": "unordered_set", "relation": "imports", "confidence": "EXTRACTED", "source_file": "C:\\Users\\boris\\OneDrive\\Documents\\GitHub\\spann\\mesh-daemon\\src\\main.cpp", "source_location": "L8", "weight": 1.0}, {"source": "c_users_boris_onedrive_documents_github_spann_mesh_daemon_src_main_cpp", "target": "vector", "relation": "imports", "confidence": "EXTRACTED", "source_file": "C:\\Users\\boris\\OneDrive\\Documents\\GitHub\\spann\\mesh-daemon\\src\\main.cpp", "source_location": "L9", "weight": 1.0}, {"source": "c_users_boris_onedrive_documents_github_spann_mesh_daemon_src_main_cpp", "target": "handlers", "relation": "imports", "confidence": "EXTRACTED", "source_file": "C:\\Users\\boris\\OneDrive\\Documents\\GitHub\\spann\\mesh-daemon\\src\\main.cpp", "source_location": "L11", "weight": 1.0}, {"source": "c_users_boris_onedrive_documents_github_spann_mesh_daemon_src_main_cpp", "target": "http_server", "relation": "imports", "confidence": "EXTRACTED", "source_file": "C:\\Users\\boris\\OneDrive\\Documents\\GitHub\\spann\\mesh-daemon\\src\\main.cpp", "source_location": "L12", "weight": 1.0}, {"source": "c_users_boris_onedrive_documents_github_spann_mesh_daemon_src_main_cpp", "target": "advertiser", "relation": "imports", "confidence": "EXTRACTED", "source_file": "C:\\Users\\boris\\OneDrive\\Documents\\GitHub\\spann\\mesh-daemon\\src\\main.cpp", "source_location": "L13", "weight": 1.0}, {"source": "c_users_boris_onedrive_documents_github_spann_mesh_daemon_src_main_cpp", "target": "gatt_server", "relation": "imports", "confidence": "EXTRACTED", "source_file": "C:\\Users\\boris\\OneDrive\\Documents\\GitHub\\spann\\mesh-daemon\\src\\main.cpp", "source_location": "L14", "weight": 1.0}, {"source": "c_users_boris_onedrive_documents_github_spann_mesh_daemon_src_main_cpp", "target": "scanner", "relation": "imports", "confidence": "EXTRACTED", "source_file": "C:\\Users\\boris\\OneDrive\\Documents\\GitHub\\spann\\mesh-daemon\\src\\main.cpp", "source_location": "L15", "weight": 1.0}, {"source": "c_users_boris_onedrive_documents_github_spann_mesh_daemon_src_main_cpp", "target": "failover", "relation": "imports", "confidence": "EXTRACTED", "source_file": "C:\\Users\\boris\\OneDrive\\Documents\\GitHub\\spann\\mesh-daemon\\src\\main.cpp", "source_location": "L16", "weight": 1.0}, {"source": "c_users_boris_onedrive_documents_github_spann_mesh_daemon_src_main_cpp", "target": "reachability", "relation": "imports", "confidence": "EXTRACTED", "source_file": "C:\\Users\\boris\\OneDrive\\Documents\\GitHub\\spann\\mesh-daemon\\src\\main.cpp", "source_location": "L17", "weight": 1.0}, {"source": "c_users_boris_onedrive_documents_github_spann_mesh_daemon_src_main_cpp", "target": "dedup_filter", "relation": "imports", "confidence": "EXTRACTED", "source_file": "C:\\Users\\boris\\OneDrive\\Documents\\GitHub\\spann\\mesh-daemon\\src\\main.cpp", "source_location": "L18", "weight": 1.0}, {"source": "c_users_boris_onedrive_documents_github_spann_mesh_daemon_src_main_cpp", "target": "epidemic_router", "relation": "imports", "confidence": "EXTRACTED", "source_file": "C:\\Users\\boris\\OneDrive\\Documents\\GitHub\\spann\\mesh-daemon\\src\\main.cpp", "source_location": "L19", "weight": 1.0}, {"source": "c_users_boris_onedrive_documents_github_spann_mesh_daemon_src_main_cpp", "target": "message_store", "relation": "imports", "confidence": "EXTRACTED", "source_file": "C:\\Users\\boris\\OneDrive\\Documents\\GitHub\\spann\\mesh-daemon\\src\\main.cpp", "source_location": "L20", "weight": 1.0}, {"source": "c_users_boris_onedrive_documents_github_spann_mesh_daemon_src_main_cpp", "target": "types", "relation": "imports", "confidence": "EXTRACTED", "source_file": "C:\\Users\\boris\\OneDrive\\Documents\\GitHub\\spann\\mesh-daemon\\src\\main.cpp", "source_location": "L21", "weight": 1.0}, {"source": "c_users_boris_onedrive_documents_github_spann_mesh_daemon_src_main_cpp", "target": "logger", "relation": "imports", "confidence": "EXTRACTED", "source_file": "C:\\Users\\boris\\OneDrive\\Documents\\GitHub\\spann\\mesh-daemon\\src\\main.cpp", "source_location": "L22", "weight": 1.0}, {"source": "c_users_boris_onedrive_documents_github_spann_mesh_daemon_src_main_cpp", "target": "peer_connection", "relation": "imports", "confidence": "EXTRACTED", "source_file": "C:\\Users\\boris\\OneDrive\\Documents\\GitHub\\spann\\mesh-daemon\\src\\main.cpp", "source_location": "L23", "weight": 1.0}, {"source": "c_users_boris_onedrive_documents_github_spann_mesh_daemon_src_main_cpp", "target": "main_handlesignal", "relation": "contains", "confidence": "EXTRACTED", "source_file": "C:\\Users\\boris\\OneDrive\\Documents\\GitHub\\spann\\mesh-daemon\\src\\main.cpp", "source_location": "L28", "weight": 1.0}, {"source": "c_users_boris_onedrive_documents_github_spann_mesh_daemon_src_main_cpp", "target": "main_getenvordefault", "relation": "contains", "confidence": "EXTRACTED", "source_file": "C:\\Users\\boris\\OneDrive\\Documents\\GitHub\\spann\\mesh-daemon\\src\\main.cpp", "source_location": "L30", "weight": 1.0}, {"source": "c_users_boris_onedrive_documents_github_spann_mesh_daemon_src_main_cpp", "target": "main_parseportordefault", "relation": "contains", "confidence": "EXTRACTED", "source_file": "C:\\Users\\boris\\OneDrive\\Documents\\GitHub\\spann\\mesh-daemon\\src\\main.cpp", "source_location": "L35", "weight": 1.0}, {"source": "c_users_boris_onedrive_documents_github_spann_mesh_daemon_src_main_cpp", "target": "main_main", "relation": "contains", "confidence": "EXTRACTED", "source_file": "C:\\Users\\boris\\OneDrive\\Documents\\GitHub\\spann\\mesh-daemon\\src\\main.cpp", "source_location": "L49", "weight": 1.0}, {"source": "main_main", "target": "main_getenvordefault", "relation": "calls", "confidence": "EXTRACTED", "source_file": "C:\\Users\\boris\\OneDrive\\Documents\\GitHub\\spann\\mesh-daemon\\src\\main.cpp", "source_location": "L53", "weight": 1.0}, {"source": "main_main", "target": "main_parseportordefault", "relation": "calls", "confidence": "EXTRACTED", "source_file": "C:\\Users\\boris\\OneDrive\\Documents\\GitHub\\spann\\mesh-daemon\\src\\main.cpp", "source_location": "L57", "weight": 1.0}], "raw_calls": [{"caller_nid": "main_handlesignal", "callee": "store", "source_file": "C:\\Users\\boris\\OneDrive\\Documents\\GitHub\\spann\\mesh-daemon\\src\\main.cpp", "source_location": "L28"}, {"caller_nid": "main_getenvordefault", "callee": "getenv", "source_file": "C:\\Users\\boris\\OneDrive\\Documents\\GitHub\\spann\\mesh-daemon\\src\\main.cpp", "source_location": "L31"}, {"caller_nid": "main_parseportordefault", "callee": "stoul", "source_file": "C:\\Users\\boris\\OneDrive\\Documents\\GitHub\\spann\\mesh-daemon\\src\\main.cpp", "source_location": "L37"}, {"caller_nid": "main_main", "callee": "signal", "source_file": "C:\\Users\\boris\\OneDrive\\Documents\\GitHub\\spann\\mesh-daemon\\src\\main.cpp", "source_location": "L50"}, {"caller_nid": "main_main", "callee": "signal", "source_file": "C:\\Users\\boris\\OneDrive\\Documents\\GitHub\\spann\\mesh-daemon\\src\\main.cpp", "source_location": "L51"}, {"caller_nid": "main_main", "callee": "Warn", "source_file": "C:\\Users\\boris\\OneDrive\\Documents\\GitHub\\spann\\mesh-daemon\\src\\main.cpp", "source_location": "L60"}, {"caller_nid": "main_main", "callee": "utils::Logger::Instance", "source_file": "C:\\Users\\boris\\OneDrive\\Documents\\GitHub\\spann\\mesh-daemon\\src\\main.cpp", "source_location": "L60"}, {"caller_nid": "main_main", "callee": "Info", "source_file": "C:\\Users\\boris\\OneDrive\\Documents\\GitHub\\spann\\mesh-daemon\\src\\main.cpp", "source_location": "L65"}, {"caller_nid": "main_main", "callee": "utils::Logger::Instance", "source_file": "C:\\Users\\boris\\OneDrive\\Documents\\GitHub\\spann\\mesh-daemon\\src\\main.cpp", "source_location": "L65"}, {"caller_nid": "main_main", "callee": "to_string", "source_file": "C:\\Users\\boris\\OneDrive\\Documents\\GitHub\\spann\\mesh-daemon\\src\\main.cpp", "source_location": "L65"}, {"caller_nid": "main_main", "callee": "chrono::seconds", "source_file": "C:\\Users\\boris\\OneDrive\\Documents\\GitHub\\spann\\mesh-daemon\\src\\main.cpp", "source_location": "L72"}, {"caller_nid": "main_main", "callee": "GetPeers", "source_file": "C:\\Users\\boris\\OneDrive\\Documents\\GitHub\\spann\\mesh-daemon\\src\\main.cpp", "source_location": "L80"}, {"caller_nid": "main_main", "callee": "insert", "source_file": "C:\\Users\\boris\\OneDrive\\Documents\\GitHub\\spann\\mesh-daemon\\src\\main.cpp", "source_location": "L84"}, {"caller_nid": "main_main", "callee": "ConnectedPeerIds", "source_file": "C:\\Users\\boris\\OneDrive\\Documents\\GitHub\\spann\\mesh-daemon\\src\\main.cpp", "source_location": "L87"}, {"caller_nid": "main_main", "callee": "contains", "source_file": "C:\\Users\\boris\\OneDrive\\Documents\\GitHub\\spann\\mesh-daemon\\src\\main.cpp", "source_location": "L88"}, {"caller_nid": "main_main", "callee": "push_back", "source_file": "C:\\Users\\boris\\OneDrive\\Documents\\GitHub\\spann\\mesh-daemon\\src\\main.cpp", "source_location": "L89"}, {"caller_nid": "main_main", "callee": "SendToPeer", "source_file": "C:\\Users\\boris\\OneDrive\\Documents\\GitHub\\spann\\mesh-daemon\\src\\main.cpp", "source_location": "L98"}, {"caller_nid": "main_main", "callee": "SetMessageHandler", "source_file": "C:\\Users\\boris\\OneDrive\\Documents\\GitHub\\spann\\mesh-daemon\\src\\main.cpp", "source_location": "L107"}, {"caller_nid": "main_main", "callee": "OnMessageReceived", "source_file": "C:\\Users\\boris\\OneDrive\\Documents\\GitHub\\spann\\mesh-daemon\\src\\main.cpp", "source_location": "L108"}, {"caller_nid": "main_main", "callee": "SetCallback", "source_file": "C:\\Users\\boris\\OneDrive\\Documents\\GitHub\\spann\\mesh-daemon\\src\\main.cpp", "source_location": "L111"}, {"caller_nid": "main_main", "callee": "Info", "source_file": "C:\\Users\\boris\\OneDrive\\Documents\\GitHub\\spann\\mesh-daemon\\src\\main.cpp", "source_location": "L112"}, {"caller_nid": "main_main", "callee": "utils::Logger::Instance", "source_file": "C:\\Users\\boris\\OneDrive\\Documents\\GitHub\\spann\\mesh-daemon\\src\\main.cpp", "source_location": "L112"}, {"caller_nid": "main_main", "callee": "Start", "source_file": "C:\\Users\\boris\\OneDrive\\Documents\\GitHub\\spann\\mesh-daemon\\src\\main.cpp", "source_location": "L117"}, {"caller_nid": "main_main", "callee": "OnReachabilityChanged", "source_file": "C:\\Users\\boris\\OneDrive\\Documents\\GitHub\\spann\\mesh-daemon\\src\\main.cpp", "source_location": "L118"}, {"caller_nid": "main_main", "callee": "Start", "source_file": "C:\\Users\\boris\\OneDrive\\Documents\\GitHub\\spann\\mesh-daemon\\src\\main.cpp", "source_location": "L121"}, {"caller_nid": "main_main", "callee": "Start", "source_file": "C:\\Users\\boris\\OneDrive\\Documents\\GitHub\\spann\\mesh-daemon\\src\\main.cpp", "source_location": "L122"}, {"caller_nid": "main_main", "callee": "Start", "source_file": "C:\\Users\\boris\\OneDrive\\Documents\\GitHub\\spann\\mesh-daemon\\src\\main.cpp", "source_location": "L123"}, {"caller_nid": "main_main", "callee": "ListPending", "source_file": "C:\\Users\\boris\\OneDrive\\Documents\\GitHub\\spann\\mesh-daemon\\src\\main.cpp", "source_location": "L127"}, {"caller_nid": "main_main", "callee": "Remove", "source_file": "C:\\Users\\boris\\OneDrive\\Documents\\GitHub\\spann\\mesh-daemon\\src\\main.cpp", "source_location": "L128"}, {"caller_nid": "main_main", "callee": "Info", "source_file": "C:\\Users\\boris\\OneDrive\\Documents\\GitHub\\spann\\mesh-daemon\\src\\main.cpp", "source_location": "L132"}, {"caller_nid": "main_main", "callee": "utils::Logger::Instance", "source_file": "C:\\Users\\boris\\OneDrive\\Documents\\GitHub\\spann\\mesh-daemon\\src\\main.cpp", "source_location": "L132"}, {"caller_nid": "main_main", "callee": "to_string", "source_file": "C:\\Users\\boris\\OneDrive\\Documents\\GitHub\\spann\\mesh-daemon\\src\\main.cpp", "source_location": "L132"}, {"caller_nid": "main_main", "callee": "Start", "source_file": "C:\\Users\\boris\\OneDrive\\Documents\\GitHub\\spann\\mesh-daemon\\src\\main.cpp", "source_location": "L138"}, {"caller_nid": "main_main", "callee": "load", "source_file": "C:\\Users\\boris\\OneDrive\\Documents\\GitHub\\spann\\mesh-daemon\\src\\main.cpp", "source_location": "L140"}, {"caller_nid": "main_main", "callee": "this_thread::sleep_for", "source_file": "C:\\Users\\boris\\OneDrive\\Documents\\GitHub\\spann\\mesh-daemon\\src\\main.cpp", "source_location": "L141"}, {"caller_nid": "main_main", "callee": "chrono::seconds", "source_file": "C:\\Users\\boris\\OneDrive\\Documents\\GitHub\\spann\\mesh-daemon\\src\\main.cpp", "source_location": "L141"}, {"caller_nid": "main_main", "callee": "Stop", "source_file": "C:\\Users\\boris\\OneDrive\\Documents\\GitHub\\spann\\mesh-daemon\\src\\main.cpp", "source_location": "L144"}, {"caller_nid": "main_main", "callee": "Stop", "source_file": "C:\\Users\\boris\\OneDrive\\Documents\\GitHub\\spann\\mesh-daemon\\src\\main.cpp", "source_location": "L145"}, {"caller_nid": "main_main", "callee": "Stop", "source_file": "C:\\Users\\boris\\OneDrive\\Documents\\GitHub\\spann\\mesh-daemon\\src\\main.cpp", "source_location": "L146"}, {"caller_nid": "main_main", "callee": "Stop", "source_file": "C:\\Users\\boris\\OneDrive\\Documents\\GitHub\\spann\\mesh-daemon\\src\\main.cpp", "source_location": "L147"}, {"caller_nid": "main_main", "callee": "Stop", "source_file": "C:\\Users\\boris\\OneDrive\\Documents\\GitHub\\spann\\mesh-daemon\\src\\main.cpp", "source_location": "L148"}, {"caller_nid": "main_main", "callee": "Info", "source_file": "C:\\Users\\boris\\OneDrive\\Documents\\GitHub\\spann\\mesh-daemon\\src\\main.cpp", "source_location": "L150"}, {"caller_nid": "main_main", "callee": "utils::Logger::Instance", "source_file": "C:\\Users\\boris\\OneDrive\\Documents\\GitHub\\spann\\mesh-daemon\\src\\main.cpp", "source_location": "L150"}]}